odoo/addons/mandate_partner_bank_creation/__init__.py
odoo/addons/mandate_partner_bank_creation/__manifest__.py
odoo/addons/mandate_partner_bank_creation/demo/partner.xml
odoo/addons/mandate_partner_bank_creation/listeners/__init__.py
odoo/addons/mandate_partner_bank_creation/listeners/partner_bank_listener.py
odoo/addons/mandate_partner_bank_creation/tests/__init__.py
odoo/addons/mandate_partner_bank_creation/tests/test_cases.py
odoo/addons/mandate_partner_bank_creation/tests/test_partner_bank_listener.py
odoo_addon_mandate_partner_bank_creation-16.0.1.0.2.dist-info/METADATA
odoo_addon_mandate_partner_bank_creation-16.0.1.0.2.dist-info/WHEEL
odoo_addon_mandate_partner_bank_creation-16.0.1.0.2.dist-info/top_level.txt
odoo_addon_mandate_partner_bank_creation-16.0.1.0.2.dist-info/RECORD
