Metadata-Version: 2.1
Name: odoo-addon-mandate-partner-bank-creation
Version: 16.0.1.0.2
Summary: When a Res Partner Bank is created, a Account Banking Mandate is created too
Home-page: https://coopdevs.org
Author: Coopdevs Treball SCCL
License: AGPL-3
Platform: UNKNOWN
Classifier: Programming Language :: Python
Classifier: Framework :: Odoo
Classifier: Framework :: Odoo :: 16.0
Classifier: License :: OSI Approved :: GNU Affero General Public License v3
Requires-Python: >=3.10
Requires-Dist: odoo-addon-account-banking-mandate (<16.1dev,>=16.0dev)
Requires-Dist: odoo-addon-account-banking-sepa-direct-debit (<16.1dev,>=16.0dev)
Requires-Dist: odoo-addon-component-event (<16.1dev,>=16.0dev)
Requires-Dist: odoo-addon-partner-manual-rank (<16.1dev,>=16.0dev)
Requires-Dist: odoo (<16.1dev,>=16.0a)
